{
  "generatedAt": "2026-05-31T18:07:54Z",
  "dateFrom": "2026-01-22",
  "dateTo": "2026-05-29",
  "totalChecks": 198828,
  "totalDelays": 634,
  "weeklyTrend": {
    "bakerloo": [
      {
        "week": "2026-W06",
        "pct": 22.8,
        "total": 3125
      },
      {
        "week": "2026-W07",
        "pct": 30.8,
        "total": 3145
      },
      {
        "week": "2026-W08",
        "pct": 18.9,
        "total": 3074
      },
      {
        "week": "2026-W09",
        "pct": 26.3,
        "total": 3113
      },
      {
        "week": "2026-W10",
        "pct": 18.9,
        "total": 3117
      },
      {
        "week": "2026-W11",
        "pct": 16.5,
        "total": 3005
      },
      {
        "week": "2026-W12",
        "pct": 15.9,
        "total": 3067
      },
      {
        "week": "2026-W13",
        "pct": 30.5,
        "total": 3018
      },
      {
        "week": "2026-W14",
        "pct": 38.7,
        "total": 2979
      },
      {
        "week": "2026-W15",
        "pct": 27.8,
        "total": 3061
      },
      {
        "week": "2026-W16",
        "pct": 45.4,
        "total": 3198
      },
      {
        "week": "2026-W17",
        "pct": 10.3,
        "total": 3039
      },
      {
        "week": "2026-W18",
        "pct": 5.6,
        "total": 3042
      },
      {
        "week": "2026-W19",
        "pct": 6.7,
        "total": 3112
      },
      {
        "week": "2026-W20",
        "pct": 2.3,
        "total": 3127
      },
      {
        "week": "2026-W21",
        "pct": 26.0,
        "total": 3106
      }
    ],
    "circle": [
      {
        "week": "2026-W06",
        "pct": 4.9,
        "total": 2555
      },
      {
        "week": "2026-W07",
        "pct": 6.9,
        "total": 3147
      },
      {
        "week": "2026-W08",
        "pct": 3.6,
        "total": 3074
      },
      {
        "week": "2026-W09",
        "pct": 1.4,
        "total": 3130
      },
      {
        "week": "2026-W10",
        "pct": 7.8,
        "total": 3128
      },
      {
        "week": "2026-W11",
        "pct": 28.4,
        "total": 3030
      },
      {
        "week": "2026-W12",
        "pct": 10.7,
        "total": 3041
      },
      {
        "week": "2026-W13",
        "pct": 10.3,
        "total": 3020
      },
      {
        "week": "2026-W14",
        "pct": 9.2,
        "total": 2964
      },
      {
        "week": "2026-W15",
        "pct": 6.0,
        "total": 3076
      },
      {
        "week": "2026-W16",
        "pct": 58.2,
        "total": 3199
      },
      {
        "week": "2026-W17",
        "pct": 17.6,
        "total": 3032
      },
      {
        "week": "2026-W18",
        "pct": 3.9,
        "total": 3058
      },
      {
        "week": "2026-W19",
        "pct": 11.6,
        "total": 3112
      },
      {
        "week": "2026-W20",
        "pct": 17.8,
        "total": 3122
      },
      {
        "week": "2026-W21",
        "pct": 41.5,
        "total": 3112
      }
    ],
    "hammersmith-city": [
      {
        "week": "2026-W06",
        "pct": 0.0,
        "total": 2435
      },
      {
        "week": "2026-W07",
        "pct": 0.0,
        "total": 3036
      },
      {
        "week": "2026-W08",
        "pct": 0.0,
        "total": 2955
      },
      {
        "week": "2026-W09",
        "pct": 1.4,
        "total": 3129
      },
      {
        "week": "2026-W10",
        "pct": 0.0,
        "total": 2631
      },
      {
        "week": "2026-W11",
        "pct": 1.9,
        "total": 2424
      },
      {
        "week": "2026-W12",
        "pct": 0.0,
        "total": 3003
      },
      {
        "week": "2026-W13",
        "pct": 0.0,
        "total": 2249
      },
      {
        "week": "2026-W14",
        "pct": 0.0,
        "total": 2068
      },
      {
        "week": "2026-W15",
        "pct": 0.0,
        "total": 2893
      },
      {
        "week": "2026-W16",
        "pct": 30.1,
        "total": 2317
      },
      {
        "week": "2026-W17",
        "pct": 0.0,
        "total": 2540
      },
      {
        "week": "2026-W18",
        "pct": 0.0,
        "total": 2702
      },
      {
        "week": "2026-W19",
        "pct": 0.0,
        "total": 2672
      },
      {
        "week": "2026-W20",
        "pct": 3.2,
        "total": 2907
      },
      {
        "week": "2026-W21",
        "pct": 4.3,
        "total": 1990
      }
    ],
    "metropolitan": [
      {
        "week": "2026-W03",
        "pct": 5.0,
        "total": 2659
      },
      {
        "week": "2026-W04",
        "pct": 11.4,
        "total": 2996
      },
      {
        "week": "2026-W05",
        "pct": 18.2,
        "total": 3131
      },
      {
        "week": "2026-W06",
        "pct": 9.0,
        "total": 3127
      },
      {
        "week": "2026-W07",
        "pct": 45.9,
        "total": 3239
      },
      {
        "week": "2026-W08",
        "pct": 16.7,
        "total": 3093
      },
      {
        "week": "2026-W09",
        "pct": 9.9,
        "total": 3116
      },
      {
        "week": "2026-W10",
        "pct": 23.0,
        "total": 3138
      },
      {
        "week": "2026-W11",
        "pct": 39.0,
        "total": 3068
      },
      {
        "week": "2026-W12",
        "pct": 16.9,
        "total": 3087
      },
      {
        "week": "2026-W13",
        "pct": 15.4,
        "total": 3083
      },
      {
        "week": "2026-W14",
        "pct": 14.7,
        "total": 3033
      },
      {
        "week": "2026-W15",
        "pct": 4.7,
        "total": 3087
      },
      {
        "week": "2026-W16",
        "pct": 65.4,
        "total": 3247
      },
      {
        "week": "2026-W17",
        "pct": 18.5,
        "total": 3079
      },
      {
        "week": "2026-W18",
        "pct": 26.7,
        "total": 3192
      },
      {
        "week": "2026-W19",
        "pct": 17.9,
        "total": 3126
      },
      {
        "week": "2026-W20",
        "pct": 8.2,
        "total": 3128
      },
      {
        "week": "2026-W21",
        "pct": 24.1,
        "total": 3120
      }
    ]
  },
  "heatmapData": {
    "bakerloo": [
      {
        "x": 5,
        "y": 0,
        "v": 7.7
      },
      {
        "x": 6,
        "y": 0,
        "v": 16.8
      },
      {
        "x": 7,
        "y": 0,
        "v": 37.9
      },
      {
        "x": 8,
        "y": 0,
        "v": 43.3
      },
      {
        "x": 9,
        "y": 0,
        "v": 26.8
      },
      {
        "x": 10,
        "y": 0,
        "v": 13.4
      },
      {
        "x": 11,
        "y": 0,
        "v": 7.5
      },
      {
        "x": 12,
        "y": 0,
        "v": 7.6
      },
      {
        "x": 13,
        "y": 0,
        "v": 15.7
      },
      {
        "x": 14,
        "y": 0,
        "v": 24.2
      },
      {
        "x": 15,
        "y": 0,
        "v": 37.5
      },
      {
        "x": 16,
        "y": 0,
        "v": 36.2
      },
      {
        "x": 17,
        "y": 0,
        "v": 41.0
      },
      {
        "x": 18,
        "y": 0,
        "v": 40.9
      },
      {
        "x": 19,
        "y": 0,
        "v": 31.6
      },
      {
        "x": 20,
        "y": 0,
        "v": 26.3
      },
      {
        "x": 21,
        "y": 0,
        "v": 25.7
      },
      {
        "x": 22,
        "y": 0,
        "v": 26.2
      },
      {
        "x": 23,
        "y": 0,
        "v": 31.7
      },
      {
        "x": 5,
        "y": 1,
        "v": 0.4
      },
      {
        "x": 6,
        "y": 1,
        "v": 5.4
      },
      {
        "x": 7,
        "y": 1,
        "v": 14.5
      },
      {
        "x": 8,
        "y": 1,
        "v": 23.5
      },
      {
        "x": 9,
        "y": 1,
        "v": 22.5
      },
      {
        "x": 10,
        "y": 1,
        "v": 11.2
      },
      {
        "x": 11,
        "y": 1,
        "v": 1.7
      },
      {
        "x": 12,
        "y": 1,
        "v": 2.7
      },
      {
        "x": 13,
        "y": 1,
        "v": 19.9
      },
      {
        "x": 14,
        "y": 1,
        "v": 25.2
      },
      {
        "x": 15,
        "y": 1,
        "v": 22.2
      },
      {
        "x": 16,
        "y": 1,
        "v": 23.3
      },
      {
        "x": 17,
        "y": 1,
        "v": 34.6
      },
      {
        "x": 18,
        "y": 1,
        "v": 36.8
      },
      {
        "x": 19,
        "y": 1,
        "v": 26.6
      },
      {
        "x": 20,
        "y": 1,
        "v": 17.4
      },
      {
        "x": 21,
        "y": 1,
        "v": 12.7
      },
      {
        "x": 22,
        "y": 1,
        "v": 12.3
      },
      {
        "x": 23,
        "y": 1,
        "v": 16.4
      },
      {
        "x": 5,
        "y": 2,
        "v": 11.9
      },
      {
        "x": 6,
        "y": 2,
        "v": 16.6
      },
      {
        "x": 7,
        "y": 2,
        "v": 37.5
      },
      {
        "x": 8,
        "y": 2,
        "v": 35.7
      },
      {
        "x": 9,
        "y": 2,
        "v": 41.0
      },
      {
        "x": 10,
        "y": 2,
        "v": 22.5
      },
      {
        "x": 11,
        "y": 2,
        "v": 26.9
      },
      {
        "x": 12,
        "y": 2,
        "v": 23.1
      },
      {
        "x": 13,
        "y": 2,
        "v": 18.5
      },
      {
        "x": 14,
        "y": 2,
        "v": 21.7
      },
      {
        "x": 15,
        "y": 2,
        "v": 26.8
      },
      {
        "x": 16,
        "y": 2,
        "v": 35.6
      },
      {
        "x": 17,
        "y": 2,
        "v": 45.0
      },
      {
        "x": 18,
        "y": 2,
        "v": 43.7
      },
      {
        "x": 19,
        "y": 2,
        "v": 39.4
      },
      {
        "x": 20,
        "y": 2,
        "v": 24.9
      },
      {
        "x": 21,
        "y": 2,
        "v": 28.4
      },
      {
        "x": 22,
        "y": 2,
        "v": 25.5
      },
      {
        "x": 23,
        "y": 2,
        "v": 23.7
      },
      {
        "x": 5,
        "y": 3,
        "v": 5.5
      },
      {
        "x": 6,
        "y": 3,
        "v": 12.7
      },
      {
        "x": 7,
        "y": 3,
        "v": 28.9
      },
      {
        "x": 8,
        "y": 3,
        "v": 34.9
      },
      {
        "x": 9,
        "y": 3,
        "v": 30.2
      },
      {
        "x": 10,
        "y": 3,
        "v": 6.2
      },
      {
        "x": 11,
        "y": 3,
        "v": 0.2
      },
      {
        "x": 12,
        "y": 3,
        "v": 11.4
      },
      {
        "x": 13,
        "y": 3,
        "v": 6.2
      },
      {
        "x": 14,
        "y": 3,
        "v": 14.3
      },
      {
        "x": 15,
        "y": 3,
        "v": 17.3
      },
      {
        "x": 16,
        "y": 3,
        "v": 25.9
      },
      {
        "x": 17,
        "y": 3,
        "v": 30.4
      },
      {
        "x": 18,
        "y": 3,
        "v": 30.5
      },
      {
        "x": 19,
        "y": 3,
        "v": 22.1
      },
      {
        "x": 20,
        "y": 3,
        "v": 12.8
      },
      {
        "x": 21,
        "y": 3,
        "v": 13.2
      },
      {
        "x": 22,
        "y": 3,
        "v": 17.9
      },
      {
        "x": 23,
        "y": 3,
        "v": 15.1
      },
      {
        "x": 5,
        "y": 4,
        "v": 14.8
      },
      {
        "x": 6,
        "y": 4,
        "v": 32.9
      },
      {
        "x": 7,
        "y": 4,
        "v": 36.9
      },
      {
        "x": 8,
        "y": 4,
        "v": 33.5
      },
      {
        "x": 9,
        "y": 4,
        "v": 22.9
      },
      {
        "x": 10,
        "y": 4,
        "v": 18.7
      },
      {
        "x": 11,
        "y": 4,
        "v": 13.7
      },
      {
        "x": 12,
        "y": 4,
        "v": 12.6
      },
      {
        "x": 13,
        "y": 4,
        "v": 15.7
      },
      {
        "x": 14,
        "y": 4,
        "v": 20.3
      },
      {
        "x": 15,
        "y": 4,
        "v": 22.4
      },
      {
        "x": 16,
        "y": 4,
        "v": 26.2
      },
      {
        "x": 17,
        "y": 4,
        "v": 22.2
      },
      {
        "x": 18,
        "y": 4,
        "v": 24.4
      },
      {
        "x": 19,
        "y": 4,
        "v": 29.1
      },
      {
        "x": 20,
        "y": 4,
        "v": 20.3
      },
      {
        "x": 21,
        "y": 4,
        "v": 17.3
      },
      {
        "x": 22,
        "y": 4,
        "v": 20.3
      },
      {
        "x": 23,
        "y": 4,
        "v": 23.5
      }
    ],
    "circle": [
      {
        "x": 5,
        "y": 0,
        "v": 2.0
      },
      {
        "x": 6,
        "y": 0,
        "v": 0.0
      },
      {
        "x": 7,
        "y": 0,
        "v": 4.6
      },
      {
        "x": 8,
        "y": 0,
        "v": 18.6
      },
      {
        "x": 9,
        "y": 0,
        "v": 12.6
      },
      {
        "x": 10,
        "y": 0,
        "v": 6.9
      },
      {
        "x": 11,
        "y": 0,
        "v": 11.3
      },
      {
        "x": 12,
        "y": 0,
        "v": 11.2
      },
      {
        "x": 13,
        "y": 0,
        "v": 10.9
      },
      {
        "x": 14,
        "y": 0,
        "v": 10.7
      },
      {
        "x": 15,
        "y": 0,
        "v": 20.4
      },
      {
        "x": 16,
        "y": 0,
        "v": 32.2
      },
      {
        "x": 17,
        "y": 0,
        "v": 30.0
      },
      {
        "x": 18,
        "y": 0,
        "v": 22.4
      },
      {
        "x": 19,
        "y": 0,
        "v": 16.4
      },
      {
        "x": 20,
        "y": 0,
        "v": 13.2
      },
      {
        "x": 21,
        "y": 0,
        "v": 11.1
      },
      {
        "x": 22,
        "y": 0,
        "v": 10.6
      },
      {
        "x": 23,
        "y": 0,
        "v": 12.4
      },
      {
        "x": 5,
        "y": 1,
        "v": 12.5
      },
      {
        "x": 6,
        "y": 1,
        "v": 8.6
      },
      {
        "x": 7,
        "y": 1,
        "v": 9.4
      },
      {
        "x": 8,
        "y": 1,
        "v": 21.2
      },
      {
        "x": 9,
        "y": 1,
        "v": 15.9
      },
      {
        "x": 10,
        "y": 1,
        "v": 12.4
      },
      {
        "x": 11,
        "y": 1,
        "v": 11.5
      },
      {
        "x": 12,
        "y": 1,
        "v": 18.1
      },
      {
        "x": 13,
        "y": 1,
        "v": 33.3
      },
      {
        "x": 14,
        "y": 1,
        "v": 20.4
      },
      {
        "x": 15,
        "y": 1,
        "v": 18.5
      },
      {
        "x": 16,
        "y": 1,
        "v": 24.2
      },
      {
        "x": 17,
        "y": 1,
        "v": 23.5
      },
      {
        "x": 18,
        "y": 1,
        "v": 32.9
      },
      {
        "x": 19,
        "y": 1,
        "v": 23.1
      },
      {
        "x": 20,
        "y": 1,
        "v": 11.9
      },
      {
        "x": 21,
        "y": 1,
        "v": 12.0
      },
      {
        "x": 22,
        "y": 1,
        "v": 15.0
      },
      {
        "x": 23,
        "y": 1,
        "v": 19.0
      },
      {
        "x": 5,
        "y": 2,
        "v": 19.4
      },
      {
        "x": 6,
        "y": 2,
        "v": 14.7
      },
      {
        "x": 7,
        "y": 2,
        "v": 16.1
      },
      {
        "x": 8,
        "y": 2,
        "v": 18.7
      },
      {
        "x": 9,
        "y": 2,
        "v": 16.6
      },
      {
        "x": 10,
        "y": 2,
        "v": 12.7
      },
      {
        "x": 11,
        "y": 2,
        "v": 14.2
      },
      {
        "x": 12,
        "y": 2,
        "v": 18.5
      },
      {
        "x": 13,
        "y": 2,
        "v": 21.8
      },
      {
        "x": 14,
        "y": 2,
        "v": 24.8
      },
      {
        "x": 15,
        "y": 2,
        "v": 28.9
      },
      {
        "x": 16,
        "y": 2,
        "v": 22.1
      },
      {
        "x": 17,
        "y": 2,
        "v": 4.1
      },
      {
        "x": 18,
        "y": 2,
        "v": 7.7
      },
      {
        "x": 19,
        "y": 2,
        "v": 12.4
      },
      {
        "x": 20,
        "y": 2,
        "v": 6.9
      },
      {
        "x": 21,
        "y": 2,
        "v": 6.3
      },
      {
        "x": 22,
        "y": 2,
        "v": 17.6
      },
      {
        "x": 23,
        "y": 2,
        "v": 17.1
      },
      {
        "x": 5,
        "y": 3,
        "v": 0.0
      },
      {
        "x": 6,
        "y": 3,
        "v": 10.3
      },
      {
        "x": 7,
        "y": 3,
        "v": 17.9
      },
      {
        "x": 8,
        "y": 3,
        "v": 20.2
      },
      {
        "x": 9,
        "y": 3,
        "v": 17.0
      },
      {
        "x": 10,
        "y": 3,
        "v": 10.6
      },
      {
        "x": 11,
        "y": 3,
        "v": 7.8
      },
      {
        "x": 12,
        "y": 3,
        "v": 9.9
      },
      {
        "x": 13,
        "y": 3,
        "v": 33.3
      },
      {
        "x": 14,
        "y": 3,
        "v": 29.1
      },
      {
        "x": 15,
        "y": 3,
        "v": 24.6
      },
      {
        "x": 16,
        "y": 3,
        "v": 23.6
      },
      {
        "x": 17,
        "y": 3,
        "v": 18.1
      },
      {
        "x": 18,
        "y": 3,
        "v": 12.8
      },
      {
        "x": 19,
        "y": 3,
        "v": 12.7
      },
      {
        "x": 20,
        "y": 3,
        "v": 18.8
      },
      {
        "x": 21,
        "y": 3,
        "v": 20.2
      },
      {
        "x": 22,
        "y": 3,
        "v": 20.8
      },
      {
        "x": 23,
        "y": 3,
        "v": 18.0
      },
      {
        "x": 5,
        "y": 4,
        "v": 16.5
      },
      {
        "x": 6,
        "y": 4,
        "v": 9.1
      },
      {
        "x": 7,
        "y": 4,
        "v": 11.2
      },
      {
        "x": 8,
        "y": 4,
        "v": 8.9
      },
      {
        "x": 9,
        "y": 4,
        "v": 10.0
      },
      {
        "x": 10,
        "y": 4,
        "v": 10.8
      },
      {
        "x": 11,
        "y": 4,
        "v": 11.7
      },
      {
        "x": 12,
        "y": 4,
        "v": 12.0
      },
      {
        "x": 13,
        "y": 4,
        "v": 11.5
      },
      {
        "x": 14,
        "y": 4,
        "v": 12.4
      },
      {
        "x": 15,
        "y": 4,
        "v": 12.2
      },
      {
        "x": 16,
        "y": 4,
        "v": 14.4
      },
      {
        "x": 17,
        "y": 4,
        "v": 22.9
      },
      {
        "x": 18,
        "y": 4,
        "v": 19.9
      },
      {
        "x": 19,
        "y": 4,
        "v": 17.4
      },
      {
        "x": 20,
        "y": 4,
        "v": 18.8
      },
      {
        "x": 21,
        "y": 4,
        "v": 8.1
      },
      {
        "x": 22,
        "y": 4,
        "v": 12.7
      },
      {
        "x": 23,
        "y": 4,
        "v": 12.7
      }
    ],
    "hammersmith-city": [
      {
        "x": 5,
        "y": 0,
        "v": 0.0
      },
      {
        "x": 6,
        "y": 0,
        "v": 0.0
      },
      {
        "x": 7,
        "y": 0,
        "v": 0.0
      },
      {
        "x": 8,
        "y": 0,
        "v": 0.0
      },
      {
        "x": 9,
        "y": 0,
        "v": 0.0
      },
      {
        "x": 10,
        "y": 0,
        "v": 0.0
      },
      {
        "x": 11,
        "y": 0,
        "v": 0.0
      },
      {
        "x": 12,
        "y": 0,
        "v": 0.0
      },
      {
        "x": 13,
        "y": 0,
        "v": 0.0
      },
      {
        "x": 14,
        "y": 0,
        "v": 0.0
      },
      {
        "x": 15,
        "y": 0,
        "v": 0.0
      },
      {
        "x": 16,
        "y": 0,
        "v": 0.0
      },
      {
        "x": 17,
        "y": 0,
        "v": 0.0
      },
      {
        "x": 18,
        "y": 0,
        "v": 0.0
      },
      {
        "x": 19,
        "y": 0,
        "v": 0.0
      },
      {
        "x": 20,
        "y": 0,
        "v": 0.0
      },
      {
        "x": 21,
        "y": 0,
        "v": 0.0
      },
      {
        "x": 22,
        "y": 0,
        "v": 0.0
      },
      {
        "x": 23,
        "y": 0,
        "v": 0.0
      },
      {
        "x": 5,
        "y": 1,
        "v": 0.0
      },
      {
        "x": 6,
        "y": 1,
        "v": 0.0
      },
      {
        "x": 7,
        "y": 1,
        "v": 0.0
      },
      {
        "x": 8,
        "y": 1,
        "v": 0.0
      },
      {
        "x": 9,
        "y": 1,
        "v": 0.0
      },
      {
        "x": 10,
        "y": 1,
        "v": 0.0
      },
      {
        "x": 11,
        "y": 1,
        "v": 0.0
      },
      {
        "x": 12,
        "y": 1,
        "v": 2.5
      },
      {
        "x": 13,
        "y": 1,
        "v": 7.9
      },
      {
        "x": 14,
        "y": 1,
        "v": 8.2
      },
      {
        "x": 15,
        "y": 1,
        "v": 5.9
      },
      {
        "x": 16,
        "y": 1,
        "v": 0.0
      },
      {
        "x": 17,
        "y": 1,
        "v": 0.0
      },
      {
        "x": 18,
        "y": 1,
        "v": 0.0
      },
      {
        "x": 19,
        "y": 1,
        "v": 2.5
      },
      {
        "x": 20,
        "y": 1,
        "v": 6.2
      },
      {
        "x": 21,
        "y": 1,
        "v": 5.6
      },
      {
        "x": 22,
        "y": 1,
        "v": 6.4
      },
      {
        "x": 23,
        "y": 1,
        "v": 6.7
      },
      {
        "x": 5,
        "y": 2,
        "v": 6.5
      },
      {
        "x": 6,
        "y": 2,
        "v": 7.0
      },
      {
        "x": 7,
        "y": 2,
        "v": 7.3
      },
      {
        "x": 8,
        "y": 2,
        "v": 7.8
      },
      {
        "x": 9,
        "y": 2,
        "v": 7.7
      },
      {
        "x": 10,
        "y": 2,
        "v": 6.5
      },
      {
        "x": 11,
        "y": 2,
        "v": 6.6
      },
      {
        "x": 12,
        "y": 2,
        "v": 6.8
      },
      {
        "x": 13,
        "y": 2,
        "v": 7.5
      },
      {
        "x": 14,
        "y": 2,
        "v": 8.0
      },
      {
        "x": 15,
        "y": 2,
        "v": 7.7
      },
      {
        "x": 16,
        "y": 2,
        "v": 3.8
      },
      {
        "x": 17,
        "y": 2,
        "v": 0.0
      },
      {
        "x": 18,
        "y": 2,
        "v": 0.0
      },
      {
        "x": 19,
        "y": 2,
        "v": 0.0
      },
      {
        "x": 20,
        "y": 2,
        "v": 0.0
      },
      {
        "x": 21,
        "y": 2,
        "v": 0.0
      },
      {
        "x": 22,
        "y": 2,
        "v": 0.0
      },
      {
        "x": 23,
        "y": 2,
        "v": 0.0
      },
      {
        "x": 5,
        "y": 3,
        "v": 0.0
      },
      {
        "x": 6,
        "y": 3,
        "v": 0.0
      },
      {
        "x": 7,
        "y": 3,
        "v": 0.0
      },
      {
        "x": 8,
        "y": 3,
        "v": 0.0
      },
      {
        "x": 9,
        "y": 3,
        "v": 0.0
      },
      {
        "x": 10,
        "y": 3,
        "v": 0.0
      },
      {
        "x": 11,
        "y": 3,
        "v": 0.0
      },
      {
        "x": 12,
        "y": 3,
        "v": 0.0
      },
      {
        "x": 13,
        "y": 3,
        "v": 0.0
      },
      {
        "x": 14,
        "y": 3,
        "v": 6.0
      },
      {
        "x": 15,
        "y": 3,
        "v": 7.9
      },
      {
        "x": 16,
        "y": 3,
        "v": 7.4
      },
      {
        "x": 17,
        "y": 3,
        "v": 1.0
      },
      {
        "x": 18,
        "y": 3,
        "v": 0.0
      },
      {
        "x": 19,
        "y": 3,
        "v": 0.0
      },
      {
        "x": 20,
        "y": 3,
        "v": 3.5
      },
      {
        "x": 21,
        "y": 3,
        "v": 6.8
      },
      {
        "x": 22,
        "y": 3,
        "v": 6.3
      },
      {
        "x": 23,
        "y": 3,
        "v": 2.9
      },
      {
        "x": 5,
        "y": 4,
        "v": 7.1
      },
      {
        "x": 6,
        "y": 4,
        "v": 3.5
      },
      {
        "x": 7,
        "y": 4,
        "v": 0.0
      },
      {
        "x": 8,
        "y": 4,
        "v": 0.0
      },
      {
        "x": 9,
        "y": 4,
        "v": 0.0
      },
      {
        "x": 10,
        "y": 4,
        "v": 0.0
      },
      {
        "x": 11,
        "y": 4,
        "v": 0.0
      },
      {
        "x": 12,
        "y": 4,
        "v": 0.0
      },
      {
        "x": 13,
        "y": 4,
        "v": 0.0
      },
      {
        "x": 14,
        "y": 4,
        "v": 0.0
      },
      {
        "x": 15,
        "y": 4,
        "v": 0.0
      },
      {
        "x": 16,
        "y": 4,
        "v": 0.0
      },
      {
        "x": 17,
        "y": 4,
        "v": 0.0
      },
      {
        "x": 18,
        "y": 4,
        "v": 0.0
      },
      {
        "x": 19,
        "y": 4,
        "v": 0.0
      },
      {
        "x": 20,
        "y": 4,
        "v": 0.0
      },
      {
        "x": 21,
        "y": 4,
        "v": 0.0
      },
      {
        "x": 22,
        "y": 4,
        "v": 0.0
      },
      {
        "x": 23,
        "y": 4,
        "v": 0.0
      }
    ],
    "metropolitan": [
      {
        "x": 5,
        "y": 0,
        "v": 27.4
      },
      {
        "x": 6,
        "y": 0,
        "v": 23.1
      },
      {
        "x": 7,
        "y": 0,
        "v": 25.3
      },
      {
        "x": 8,
        "y": 0,
        "v": 24.8
      },
      {
        "x": 9,
        "y": 0,
        "v": 21.5
      },
      {
        "x": 10,
        "y": 0,
        "v": 16.5
      },
      {
        "x": 11,
        "y": 0,
        "v": 13.2
      },
      {
        "x": 12,
        "y": 0,
        "v": 11.3
      },
      {
        "x": 13,
        "y": 0,
        "v": 20.8
      },
      {
        "x": 14,
        "y": 0,
        "v": 22.3
      },
      {
        "x": 15,
        "y": 0,
        "v": 21.6
      },
      {
        "x": 16,
        "y": 0,
        "v": 30.3
      },
      {
        "x": 17,
        "y": 0,
        "v": 27.4
      },
      {
        "x": 18,
        "y": 0,
        "v": 23.2
      },
      {
        "x": 19,
        "y": 0,
        "v": 15.9
      },
      {
        "x": 20,
        "y": 0,
        "v": 19.9
      },
      {
        "x": 21,
        "y": 0,
        "v": 20.9
      },
      {
        "x": 22,
        "y": 0,
        "v": 17.0
      },
      {
        "x": 23,
        "y": 0,
        "v": 16.9
      },
      {
        "x": 5,
        "y": 1,
        "v": 8.7
      },
      {
        "x": 6,
        "y": 1,
        "v": 19.3
      },
      {
        "x": 7,
        "y": 1,
        "v": 19.9
      },
      {
        "x": 8,
        "y": 1,
        "v": 13.1
      },
      {
        "x": 9,
        "y": 1,
        "v": 16.1
      },
      {
        "x": 10,
        "y": 1,
        "v": 22.9
      },
      {
        "x": 11,
        "y": 1,
        "v": 30.2
      },
      {
        "x": 12,
        "y": 1,
        "v": 23.1
      },
      {
        "x": 13,
        "y": 1,
        "v": 20.7
      },
      {
        "x": 14,
        "y": 1,
        "v": 21.1
      },
      {
        "x": 15,
        "y": 1,
        "v": 21.1
      },
      {
        "x": 16,
        "y": 1,
        "v": 21.0
      },
      {
        "x": 17,
        "y": 1,
        "v": 18.5
      },
      {
        "x": 18,
        "y": 1,
        "v": 10.0
      },
      {
        "x": 19,
        "y": 1,
        "v": 8.1
      },
      {
        "x": 20,
        "y": 1,
        "v": 5.0
      },
      {
        "x": 21,
        "y": 1,
        "v": 5.0
      },
      {
        "x": 22,
        "y": 1,
        "v": 7.1
      },
      {
        "x": 23,
        "y": 1,
        "v": 12.8
      },
      {
        "x": 5,
        "y": 2,
        "v": 18.2
      },
      {
        "x": 6,
        "y": 2,
        "v": 17.1
      },
      {
        "x": 7,
        "y": 2,
        "v": 16.9
      },
      {
        "x": 8,
        "y": 2,
        "v": 25.4
      },
      {
        "x": 9,
        "y": 2,
        "v": 16.0
      },
      {
        "x": 10,
        "y": 2,
        "v": 15.3
      },
      {
        "x": 11,
        "y": 2,
        "v": 17.8
      },
      {
        "x": 12,
        "y": 2,
        "v": 22.7
      },
      {
        "x": 13,
        "y": 2,
        "v": 23.6
      },
      {
        "x": 14,
        "y": 2,
        "v": 20.1
      },
      {
        "x": 15,
        "y": 2,
        "v": 11.4
      },
      {
        "x": 16,
        "y": 2,
        "v": 14.0
      },
      {
        "x": 17,
        "y": 2,
        "v": 17.4
      },
      {
        "x": 18,
        "y": 2,
        "v": 12.9
      },
      {
        "x": 19,
        "y": 2,
        "v": 15.8
      },
      {
        "x": 20,
        "y": 2,
        "v": 22.0
      },
      {
        "x": 21,
        "y": 2,
        "v": 24.2
      },
      {
        "x": 22,
        "y": 2,
        "v": 29.2
      },
      {
        "x": 23,
        "y": 2,
        "v": 32.9
      },
      {
        "x": 5,
        "y": 3,
        "v": 15.2
      },
      {
        "x": 6,
        "y": 3,
        "v": 22.2
      },
      {
        "x": 7,
        "y": 3,
        "v": 18.6
      },
      {
        "x": 8,
        "y": 3,
        "v": 24.2
      },
      {
        "x": 9,
        "y": 3,
        "v": 20.5
      },
      {
        "x": 10,
        "y": 3,
        "v": 25.6
      },
      {
        "x": 11,
        "y": 3,
        "v": 23.3
      },
      {
        "x": 12,
        "y": 3,
        "v": 27.6
      },
      {
        "x": 13,
        "y": 3,
        "v": 18.0
      },
      {
        "x": 14,
        "y": 3,
        "v": 20.2
      },
      {
        "x": 15,
        "y": 3,
        "v": 21.2
      },
      {
        "x": 16,
        "y": 3,
        "v": 19.8
      },
      {
        "x": 17,
        "y": 3,
        "v": 13.3
      },
      {
        "x": 18,
        "y": 3,
        "v": 18.3
      },
      {
        "x": 19,
        "y": 3,
        "v": 19.7
      },
      {
        "x": 20,
        "y": 3,
        "v": 21.8
      },
      {
        "x": 21,
        "y": 3,
        "v": 19.9
      },
      {
        "x": 22,
        "y": 3,
        "v": 21.9
      },
      {
        "x": 23,
        "y": 3,
        "v": 19.5
      },
      {
        "x": 5,
        "y": 4,
        "v": 29.7
      },
      {
        "x": 6,
        "y": 4,
        "v": 38.7
      },
      {
        "x": 7,
        "y": 4,
        "v": 34.2
      },
      {
        "x": 8,
        "y": 4,
        "v": 29.7
      },
      {
        "x": 9,
        "y": 4,
        "v": 29.8
      },
      {
        "x": 10,
        "y": 4,
        "v": 20.8
      },
      {
        "x": 11,
        "y": 4,
        "v": 19.3
      },
      {
        "x": 12,
        "y": 4,
        "v": 18.3
      },
      {
        "x": 13,
        "y": 4,
        "v": 18.6
      },
      {
        "x": 14,
        "y": 4,
        "v": 16.6
      },
      {
        "x": 15,
        "y": 4,
        "v": 19.7
      },
      {
        "x": 16,
        "y": 4,
        "v": 26.1
      },
      {
        "x": 17,
        "y": 4,
        "v": 31.7
      },
      {
        "x": 18,
        "y": 4,
        "v": 29.6
      },
      {
        "x": 19,
        "y": 4,
        "v": 32.4
      },
      {
        "x": 20,
        "y": 4,
        "v": 36.0
      },
      {
        "x": 21,
        "y": 4,
        "v": 40.0
      },
      {
        "x": 22,
        "y": 4,
        "v": 41.5
      },
      {
        "x": 23,
        "y": 4,
        "v": 35.7
      }
    ]
  },
  "causeLabels": [
    "Other",
    "Faulty Train",
    "Signal Failure",
    "Fire Alert",
    "Points Failure",
    "Customer Incident",
    "Late Finish Engineering",
    "Trespass on Tracks",
    "Person Ill on Train",
    "Earlier Incident",
    "Casualty on Track",
    "Defective Train"
  ],
  "causeValues": [
    233,
    105,
    73,
    62,
    52,
    33,
    23,
    22,
    13,
    11,
    4,
    3
  ],
  "peakOffpeak": {
    "metropolitan": {
      "AM Peak (07-09)": 23.2,
      "PM Peak (17-19)": 20.1,
      "Off-Peak": 20.7
    },
    "bakerloo": {
      "AM Peak (07-09)": 32.6,
      "PM Peak (17-19)": 35.0,
      "Off-Peak": 18.6
    },
    "circle": {
      "AM Peak (07-09)": 14.7,
      "PM Peak (17-19)": 19.3,
      "Off-Peak": 14.8
    },
    "hammersmith-city": {
      "AM Peak (07-09)": 1.6,
      "PM Peak (17-19)": 0.1,
      "Off-Peak": 2.6
    }
  },
  "correlation": {
    "metropolitan": {
      "metropolitan": 2247,
      "bakerloo": 28.5,
      "circle": 34.7,
      "hammersmith-city": 6.9
    },
    "bakerloo": {
      "metropolitan": 29.5,
      "bakerloo": 2176,
      "circle": 23.1,
      "hammersmith-city": 7.0
    },
    "circle": {
      "metropolitan": 50.7,
      "bakerloo": 32.7,
      "circle": 1537,
      "hammersmith-city": 12.8
    },
    "hammersmith-city": {
      "metropolitan": 76.6,
      "bakerloo": 75.6,
      "circle": 98.0,
      "hammersmith-city": 201
    }
  },
  "calendarData": [
    {
      "date": "2026-01-22",
      "value": 16.0
    },
    {
      "date": "2026-01-23",
      "value": 252.0
    },
    {
      "date": "2026-01-26",
      "value": 318.0
    },
    {
      "date": "2026-01-29",
      "value": 68.0
    },
    {
      "date": "2026-01-30",
      "value": 300.0
    },
    {
      "date": "2026-02-02",
      "value": 246.0
    },
    {
      "date": "2026-02-03",
      "value": 448.0
    },
    {
      "date": "2026-02-04",
      "value": 100.0
    },
    {
      "date": "2026-02-06",
      "value": 344.0
    },
    {
      "date": "2026-02-09",
      "value": 766.0
    },
    {
      "date": "2026-02-10",
      "value": 644.0
    },
    {
      "date": "2026-02-11",
      "value": 314.0
    },
    {
      "date": "2026-02-12",
      "value": 370.0
    },
    {
      "date": "2026-02-13",
      "value": 146.0
    },
    {
      "date": "2026-02-16",
      "value": 960.0
    },
    {
      "date": "2026-02-17",
      "value": 518.0
    },
    {
      "date": "2026-02-18",
      "value": 744.0
    },
    {
      "date": "2026-02-19",
      "value": 1452.0
    },
    {
      "date": "2026-02-20",
      "value": 1676.0
    },
    {
      "date": "2026-02-23",
      "value": 574.0
    },
    {
      "date": "2026-02-24",
      "value": 932.0
    },
    {
      "date": "2026-02-25",
      "value": 242.0
    },
    {
      "date": "2026-02-26",
      "value": 152.0
    },
    {
      "date": "2026-02-27",
      "value": 514.0
    },
    {
      "date": "2026-03-02",
      "value": 352.0
    },
    {
      "date": "2026-03-03",
      "value": 752.0
    },
    {
      "date": "2026-03-04",
      "value": 588.0
    },
    {
      "date": "2026-03-05",
      "value": 464.0
    },
    {
      "date": "2026-03-06",
      "value": 284.0
    },
    {
      "date": "2026-03-09",
      "value": 1110.0
    },
    {
      "date": "2026-03-10",
      "value": 368.0
    },
    {
      "date": "2026-03-11",
      "value": 660.0
    },
    {
      "date": "2026-03-12",
      "value": 734.0
    },
    {
      "date": "2026-03-13",
      "value": 236.0
    },
    {
      "date": "2026-03-16",
      "value": 1322.0
    },
    {
      "date": "2026-03-17",
      "value": 606.0
    },
    {
      "date": "2026-03-18",
      "value": 2082.0
    },
    {
      "date": "2026-03-19",
      "value": 500.0
    },
    {
      "date": "2026-03-20",
      "value": 688.0
    },
    {
      "date": "2026-03-23",
      "value": 100.0
    },
    {
      "date": "2026-03-24",
      "value": 914.0
    },
    {
      "date": "2026-03-25",
      "value": 450.0
    },
    {
      "date": "2026-03-26",
      "value": 176.0
    },
    {
      "date": "2026-03-27",
      "value": 1030.0
    },
    {
      "date": "2026-03-30",
      "value": 710.0
    },
    {
      "date": "2026-03-31",
      "value": 86.0
    },
    {
      "date": "2026-04-01",
      "value": 334.0
    },
    {
      "date": "2026-04-02",
      "value": 886.0
    },
    {
      "date": "2026-04-03",
      "value": 1398.0
    },
    {
      "date": "2026-04-06",
      "value": 1300.0
    },
    {
      "date": "2026-04-07",
      "value": 336.0
    },
    {
      "date": "2026-04-08",
      "value": 1006.0
    },
    {
      "date": "2026-04-09",
      "value": 518.0
    },
    {
      "date": "2026-04-10",
      "value": 584.0
    },
    {
      "date": "2026-04-13",
      "value": 400.0
    },
    {
      "date": "2026-04-14",
      "value": 416.0
    },
    {
      "date": "2026-04-15",
      "value": 440.0
    },
    {
      "date": "2026-04-16",
      "value": 600.0
    },
    {
      "date": "2026-04-17",
      "value": 508.0
    },
    {
      "date": "2026-04-20",
      "value": 298.0
    },
    {
      "date": "2026-04-21",
      "value": 2644.0
    },
    {
      "date": "2026-04-22",
      "value": 3752.0
    },
    {
      "date": "2026-04-23",
      "value": 2606.0
    },
    {
      "date": "2026-04-24",
      "value": 2968.0
    },
    {
      "date": "2026-04-27",
      "value": 932.0
    },
    {
      "date": "2026-04-28",
      "value": 120.0
    },
    {
      "date": "2026-04-29",
      "value": 516.0
    },
    {
      "date": "2026-04-30",
      "value": 608.0
    },
    {
      "date": "2026-05-01",
      "value": 656.0
    },
    {
      "date": "2026-05-04",
      "value": 1440.0
    },
    {
      "date": "2026-05-05",
      "value": 286.0
    },
    {
      "date": "2026-05-06",
      "value": 38.0
    },
    {
      "date": "2026-05-07",
      "value": 266.0
    },
    {
      "date": "2026-05-08",
      "value": 248.0
    },
    {
      "date": "2026-05-11",
      "value": 826.0
    },
    {
      "date": "2026-05-12",
      "value": 212.0
    },
    {
      "date": "2026-05-13",
      "value": 230.0
    },
    {
      "date": "2026-05-14",
      "value": 770.0
    },
    {
      "date": "2026-05-15",
      "value": 218.0
    },
    {
      "date": "2026-05-18",
      "value": 280.0
    },
    {
      "date": "2026-05-19",
      "value": 638.0
    },
    {
      "date": "2026-05-20",
      "value": 432.0
    },
    {
      "date": "2026-05-21",
      "value": 162.0
    },
    {
      "date": "2026-05-22",
      "value": 436.0
    },
    {
      "date": "2026-05-25",
      "value": 836.0
    },
    {
      "date": "2026-05-26",
      "value": 924.0
    },
    {
      "date": "2026-05-27",
      "value": 1558.0
    },
    {
      "date": "2026-05-28",
      "value": 1348.0
    },
    {
      "date": "2026-05-29",
      "value": 1210.0
    }
  ],
  "lineDailyData": {
    "bakerloo": {
      "2026-02-09": 706.0,
      "2026-02-10": 332.0,
      "2026-02-11": 190.0,
      "2026-02-12": 138.0,
      "2026-02-13": 60.0,
      "2026-02-16": 714.0,
      "2026-02-17": 462.0,
      "2026-02-18": 480.0,
      "2026-02-19": 136.0,
      "2026-02-20": 148.0,
      "2026-02-23": 240.0,
      "2026-02-24": 426.0,
      "2026-02-25": 188.0,
      "2026-02-26": 10.0,
      "2026-02-27": 298.0,
      "2026-03-02": 172.0,
      "2026-03-03": 438.0,
      "2026-03-04": 418.0,
      "2026-03-05": 328.0,
      "2026-03-06": 284.0,
      "2026-03-09": 292.0,
      "2026-03-10": 80.0,
      "2026-03-11": 372.0,
      "2026-03-12": 424.0,
      "2026-03-13": 10.0,
      "2026-03-16": 320.0,
      "2026-03-17": 48.0,
      "2026-03-18": 402.0,
      "2026-03-19": 216.0,
      "2026-03-20": 4.0,
      "2026-03-24": 212.0,
      "2026-03-25": 94.0,
      "2026-03-26": 88.0,
      "2026-03-27": 582.0,
      "2026-03-30": 392.0,
      "2026-03-31": 70.0,
      "2026-04-02": 190.0,
      "2026-04-03": 1188.0,
      "2026-04-06": 1194.0,
      "2026-04-07": 182.0,
      "2026-04-08": 700.0,
      "2026-04-09": 110.0,
      "2026-04-10": 120.0,
      "2026-04-14": 246.0,
      "2026-04-15": 440.0,
      "2026-04-16": 600.0,
      "2026-04-17": 416.0,
      "2026-04-20": 36.0,
      "2026-04-21": 658.0,
      "2026-04-22": 758.0,
      "2026-04-23": 662.0,
      "2026-04-24": 790.0,
      "2026-04-27": 364.0,
      "2026-04-28": 26.0,
      "2026-04-29": 234.0,
      "2026-05-07": 200.0,
      "2026-05-08": 138.0,
      "2026-05-11": 38.0,
      "2026-05-12": 66.0,
      "2026-05-13": 190.0,
      "2026-05-15": 120.0,
      "2026-05-19": 18.0,
      "2026-05-20": 124.0,
      "2026-05-25": 382.0,
      "2026-05-26": 140.0,
      "2026-05-27": 714.0,
      "2026-05-28": 246.0,
      "2026-05-29": 136.0
    },
    "circle": {
      "2026-02-10": 68.0,
      "2026-02-11": 44.0,
      "2026-02-12": 140.0,
      "2026-02-16": 54.0,
      "2026-02-18": 144.0,
      "2026-02-19": 148.0,
      "2026-02-20": 88.0,
      "2026-02-24": 92.0,
      "2026-02-26": 80.0,
      "2026-02-27": 48.0,
      "2026-03-02": 90.0,
      "2026-03-09": 408.0,
      "2026-03-12": 80.0,
      "2026-03-16": 540.0,
      "2026-03-17": 524.0,
      "2026-03-18": 520.0,
      "2026-03-19": 112.0,
      "2026-03-20": 28.0,
      "2026-03-23": 58.0,
      "2026-03-24": 356.0,
      "2026-03-25": 162.0,
      "2026-03-27": 74.0,
      "2026-04-01": 210.0,
      "2026-04-02": 412.0,
      "2026-04-06": 70.0,
      "2026-04-08": 228.0,
      "2026-04-09": 246.0,
      "2026-04-13": 254.0,
      "2026-04-14": 116.0,
      "2026-04-20": 176.0,
      "2026-04-21": 914.0,
      "2026-04-22": 994.0,
      "2026-04-23": 876.0,
      "2026-04-24": 762.0,
      "2026-04-27": 304.0,
      "2026-04-28": 18.0,
      "2026-04-29": 66.0,
      "2026-04-30": 132.0,
      "2026-05-01": 550.0,
      "2026-05-05": 86.0,
      "2026-05-06": 38.0,
      "2026-05-07": 66.0,
      "2026-05-08": 48.0,
      "2026-05-11": 342.0,
      "2026-05-12": 146.0,
      "2026-05-13": 26.0,
      "2026-05-14": 208.0,
      "2026-05-18": 192.0,
      "2026-05-19": 424.0,
      "2026-05-20": 174.0,
      "2026-05-21": 80.0,
      "2026-05-22": 242.0,
      "2026-05-25": 126.0,
      "2026-05-26": 690.0,
      "2026-05-27": 428.0,
      "2026-05-28": 672.0,
      "2026-05-29": 668.0
    },
    "hammersmith-city": {
      "2026-03-02": 90.0,
      "2026-03-16": 90.0,
      "2026-04-21": 250.0,
      "2026-04-22": 772.0,
      "2026-04-23": 172.0,
      "2026-04-24": 200.0,
      "2026-05-19": 184.0,
      "2026-05-28": 170.0
    },
    "metropolitan": {
      "2026-01-22": 16.0,
      "2026-01-23": 252.0,
      "2026-01-26": 318.0,
      "2026-01-29": 68.0,
      "2026-01-30": 300.0,
      "2026-02-02": 246.0,
      "2026-02-03": 448.0,
      "2026-02-04": 100.0,
      "2026-02-06": 344.0,
      "2026-02-09": 60.0,
      "2026-02-10": 244.0,
      "2026-02-11": 80.0,
      "2026-02-12": 92.0,
      "2026-02-13": 86.0,
      "2026-02-16": 192.0,
      "2026-02-17": 56.0,
      "2026-02-18": 120.0,
      "2026-02-19": 1168.0,
      "2026-02-20": 1440.0,
      "2026-02-23": 334.0,
      "2026-02-24": 414.0,
      "2026-02-25": 54.0,
      "2026-02-26": 62.0,
      "2026-02-27": 168.0,
      "2026-03-03": 314.0,
      "2026-03-04": 170.0,
      "2026-03-05": 136.0,
      "2026-03-09": 410.0,
      "2026-03-10": 288.0,
      "2026-03-11": 288.0,
      "2026-03-12": 230.0,
      "2026-03-13": 226.0,
      "2026-03-16": 372.0,
      "2026-03-17": 34.0,
      "2026-03-18": 1160.0,
      "2026-03-19": 172.0,
      "2026-03-20": 656.0,
      "2026-03-23": 42.0,
      "2026-03-24": 346.0,
      "2026-03-25": 194.0,
      "2026-03-26": 88.0,
      "2026-03-27": 374.0,
      "2026-03-30": 318.0,
      "2026-03-31": 16.0,
      "2026-04-01": 124.0,
      "2026-04-02": 284.0,
      "2026-04-03": 210.0,
      "2026-04-06": 36.0,
      "2026-04-07": 154.0,
      "2026-04-08": 78.0,
      "2026-04-09": 162.0,
      "2026-04-10": 464.0,
      "2026-04-13": 146.0,
      "2026-04-14": 54.0,
      "2026-04-17": 92.0,
      "2026-04-20": 86.0,
      "2026-04-21": 822.0,
      "2026-04-22": 1228.0,
      "2026-04-23": 896.0,
      "2026-04-24": 1216.0,
      "2026-04-27": 264.0,
      "2026-04-28": 76.0,
      "2026-04-29": 216.0,
      "2026-04-30": 476.0,
      "2026-05-01": 106.0,
      "2026-05-04": 1440.0,
      "2026-05-05": 200.0,
      "2026-05-08": 62.0,
      "2026-05-11": 446.0,
      "2026-05-13": 14.0,
      "2026-05-14": 562.0,
      "2026-05-15": 98.0,
      "2026-05-18": 88.0,
      "2026-05-19": 12.0,
      "2026-05-20": 134.0,
      "2026-05-21": 82.0,
      "2026-05-22": 194.0,
      "2026-05-25": 328.0,
      "2026-05-26": 94.0,
      "2026-05-27": 416.0,
      "2026-05-28": 260.0,
      "2026-05-29": 406.0
    }
  },
  "streakDist": {
    "bakerloo": {
      "20": 4,
      "120": 58,
      "100": 4,
      "30": 4,
      "60": 7,
      "110": 3,
      "0": 4,
      "50": 4,
      "90": 7,
      "40": 8,
      "10": 6,
      "80": 5,
      "70": 5
    },
    "circle": {
      "60": 5,
      "40": 12,
      "90": 8,
      "30": 6,
      "10": 5,
      "50": 11,
      "120": 35,
      "70": 9,
      "0": 4,
      "80": 3,
      "100": 3,
      "110": 2,
      "20": 5
    },
    "hammersmith-city": {
      "90": 2,
      "120": 6,
      "50": 1
    },
    "metropolitan": {
      "10": 14,
      "50": 16,
      "20": 12,
      "60": 17,
      "80": 10,
      "120": 42,
      "100": 4,
      "40": 18,
      "90": 12,
      "30": 15,
      "70": 7,
      "110": 4,
      "0": 3
    }
  },
  "escalations": {
    "metropolitan": {
      "Minor Delays \u2192 Part Suspended": 24,
      "Part Suspended \u2192 Severe Delays": 37,
      "Severe Delays \u2192 Part Suspended": 25,
      "Severe Delays \u2192 Minor Delays": 51,
      "Minor Delays \u2192 Severe Delays": 39,
      "Part Suspended \u2192 Minor Delays": 12
    },
    "bakerloo": {
      "Minor Delays \u2192 Part Suspended": 24,
      "Part Suspended \u2192 Severe Delays": 18,
      "Severe Delays \u2192 Minor Delays": 32,
      "Part Suspended \u2192 Minor Delays": 10,
      "Minor Delays \u2192 Severe Delays": 19,
      "Severe Delays \u2192 Part Suspended": 4
    },
    "circle": {
      "Minor Delays \u2192 Severe Delays": 30,
      "Severe Delays \u2192 Minor Delays": 36,
      "Minor Delays \u2192 Part Suspended": 9,
      "Part Suspended \u2192 Severe Delays": 11,
      "Part Suspended \u2192 Minor Delays": 3,
      "Severe Delays \u2192 Part Suspended": 5
    }
  },
  "reliability": {
    "bakerloo": {
      "good_pct": 78.1,
      "disrupted_pct": 21.9,
      "breakdown": {
        "Good Service": 78.1,
        "Minor Delays": 11.3,
        "Severe Delays": 6.0,
        "Part Closure": 2.5,
        "Suspended": 0.9,
        "Part Suspended": 0.8,
        "Special Service": 0.4
      },
      "total_checks": 49328
    },
    "circle": {
      "good_pct": 84.4,
      "disrupted_pct": 15.6,
      "breakdown": {
        "Good Service": 84.4,
        "Minor Delays": 7.0,
        "Suspended": 3.9,
        "Severe Delays": 3.7,
        "Special Service": 0.4,
        "Part Closure": 0.3,
        "Part Suspended": 0.3
      },
      "total_checks": 48800
    },
    "hammersmith-city": {
      "good_pct": 97.2,
      "disrupted_pct": 2.8,
      "breakdown": {
        "Good Service": 97.2,
        "Suspended": 1.1,
        "Severe Delays": 1.0,
        "Special Service": 0.5,
        "Part Closure": 0.2
      },
      "total_checks": 41951
    },
    "metropolitan": {
      "good_pct": 78.8,
      "disrupted_pct": 21.2,
      "breakdown": {
        "Good Service": 78.8,
        "Minor Delays": 9.3,
        "Severe Delays": 6.2,
        "Part Closure": 3.8,
        "Part Suspended": 0.9,
        "Suspended": 0.7,
        "Special Service": 0.3
      },
      "total_checks": 58749
    }
  },
  "allWeeks": [
    "2026-W03",
    "2026-W04",
    "2026-W05",
    "2026-W06",
    "2026-W07",
    "2026-W08",
    "2026-W09",
    "2026-W10",
    "2026-W11",
    "2026-W12",
    "2026-W13",
    "2026-W14",
    "2026-W15",
    "2026-W16",
    "2026-W17",
    "2026-W18",
    "2026-W19",
    "2026-W20",
    "2026-W21"
  ]
}