{
  "timestamp": "2026-03-16T21:51:37.014201+00:00",
  "lines": {
    "metropolitan": {
      "name": "Metropolitan",
      "on_time_pct": 0,
      "total_predictions": 0,
      "avg_variance_secs": 0
    },
    "bakerloo": {
      "name": "Bakerloo",
      "on_time_pct": 98.8,
      "total_predictions": 763,
      "avg_variance_secs": 1.1
    },
    "hammersmith-city": {
      "name": "Hammersmith & City",
      "on_time_pct": 53.4,
      "total_predictions": 1161,
      "avg_variance_secs": 8.0
    },
    "circle": {
      "name": "Circle",
      "on_time_pct": 0,
      "total_predictions": 0,
      "avg_variance_secs": 0
    }
  }
}