[
  {
    "line_id": "metropolitan",
    "line_name": "Metropolitan",
    "colour": "#9B0056",
    "stations": {
      "940GZZLUBST": {
        "name": "Baker Street",
        "total_predictions": 0,
        "on_time": 0,
        "early": 0,
        "late": 0,
        "on_time_pct": 0,
        "avg_variance_secs": 0,
        "variances": []
      },
      "940GZZLUFYR": {
        "name": "Finchley Road",
        "total_predictions": 0,
        "on_time": 0,
        "early": 0,
        "late": 0,
        "on_time_pct": 0,
        "avg_variance_secs": 0,
        "variances": []
      },
      "940GZZLUMSP": {
        "name": "Moor Park",
        "total_predictions": 0,
        "on_time": 0,
        "early": 0,
        "late": 0,
        "on_time_pct": 0,
        "avg_variance_secs": 0,
        "variances": []
      },
      "940GZZLUHOH": {
        "name": "Harrow-on-the-Hill",
        "total_predictions": 0,
        "on_time": 0,
        "early": 0,
        "late": 0,
        "on_time_pct": 0,
        "avg_variance_secs": 0,
        "variances": []
      },
      "940GZZLUKSX": {
        "name": "King's Cross St. Pancras",
        "total_predictions": 0,
        "on_time": 0,
        "early": 0,
        "late": 0,
        "on_time_pct": 0,
        "avg_variance_secs": 0,
        "variances": []
      }
    },
    "timestamp": "2026-03-12T17:12:29.277918+00:00"
  },
  {
    "line_id": "bakerloo",
    "line_name": "Bakerloo",
    "colour": "#B36305",
    "stations": {
      "940GZZLUPAC": {
        "name": "Paddington",
        "total_predictions": 0,
        "on_time": 0,
        "early": 0,
        "late": 0,
        "on_time_pct": 0,
        "avg_variance_secs": 0,
        "variances": []
      },
      "940GZZLUOXC": {
        "name": "Oxford Circus",
        "total_predictions": 0,
        "on_time": 0,
        "early": 0,
        "late": 0,
        "on_time_pct": 0,
        "avg_variance_secs": 0,
        "variances": []
      },
      "940GZZLUWLO": {
        "name": "Waterloo",
        "total_predictions": 0,
        "on_time": 0,
        "early": 0,
        "late": 0,
        "on_time_pct": 0,
        "avg_variance_secs": 0,
        "variances": []
      },
      "940GZZLUEMB": {
        "name": "Embankment",
        "total_predictions": 0,
        "on_time": 0,
        "early": 0,
        "late": 0,
        "on_time_pct": 0,
        "avg_variance_secs": 0,
        "variances": []
      },
      "940GZZLUEAC": {
        "name": "Elephant & Castle",
        "total_predictions": 12,
        "on_time": 12,
        "early": 0,
        "late": 0,
        "on_time_pct": 100.0,
        "avg_variance_secs": -6.7,
        "variances": [
          {
            "vehicle_id": "204",
            "destination": "Elephant & Castle Underground Station",
            "predicted_arrival": "2026-03-12T17:34:41+00:00",
            "scheduled_time": "2026-03-12T17:35:00+00:00",
            "variance_seconds": -19,
            "time_to_station": 1351,
            "platform": "Northbound - Platform 4",
            "direction": ""
          },
          {
            "vehicle_id": "204",
            "destination": "Elephant & Castle Underground Station",
            "predicted_arrival": "2026-03-12T17:35:41+00:00",
            "scheduled_time": "2026-03-12T17:36:00+00:00",
            "variance_seconds": -19,
            "time_to_station": 1411,
            "platform": "Northbound - Platform 3",
            "direction": ""
          },
          {
            "vehicle_id": "225",
            "destination": "Elephant & Castle Underground Station",
            "predicted_arrival": "2026-03-12T17:37:41+00:00",
            "scheduled_time": "2026-03-12T17:38:00+00:00",
            "variance_seconds": -19,
            "time_to_station": 1531,
            "platform": "Northbound - Platform 3",
            "direction": ""
          },
          {
            "vehicle_id": "225",
            "destination": "Elephant & Castle Underground Station",
            "predicted_arrival": "2026-03-12T17:37:41+00:00",
            "scheduled_time": "2026-03-12T17:38:00+00:00",
            "variance_seconds": -19,
            "time_to_station": 1531,
            "platform": "Northbound - Platform 4",
            "direction": ""
          },
          {
            "vehicle_id": "242",
            "destination": "Elephant & Castle Underground Station",
            "predicted_arrival": "2026-03-12T17:22:41+00:00",
            "scheduled_time": "2026-03-12T17:23:00+00:00",
            "variance_seconds": -19,
            "time_to_station": 631,
            "platform": "Northbound - Platform 4",
            "direction": ""
          },
          {
            "vehicle_id": "226",
            "destination": "Elephant & Castle Underground Station",
            "predicted_arrival": "2026-03-12T17:26:41+00:00",
            "scheduled_time": "2026-03-12T17:26:00+00:00",
            "variance_seconds": 41,
            "time_to_station": 871,
            "platform": "Northbound - Platform 4",
            "direction": ""
          },
          {
            "vehicle_id": "212",
            "destination": "Elephant & Castle Underground Station",
            "predicted_arrival": "2026-03-12T17:13:41+00:00",
            "scheduled_time": "2026-03-12T17:14:00+00:00",
            "variance_seconds": -19,
            "time_to_station": 91,
            "platform": "Northbound - Platform 4",
            "direction": ""
          },
          {
            "vehicle_id": "226",
            "destination": "Elephant & Castle Underground Station",
            "predicted_arrival": "2026-03-12T17:26:41+00:00",
            "scheduled_time": "2026-03-12T17:26:00+00:00",
            "variance_seconds": 41,
            "time_to_station": 871,
            "platform": "Northbound - Platform 3",
            "direction": ""
          },
          {
            "vehicle_id": "240",
            "destination": "Elephant & Castle Underground Station",
            "predicted_arrival": "2026-03-12T17:28:41+00:00",
            "scheduled_time": "2026-03-12T17:29:00+00:00",
            "variance_seconds": -19,
            "time_to_station": 991,
            "platform": "Northbound - Platform 3",
            "direction": ""
          },
          {
            "vehicle_id": "240",
            "destination": "Elephant & Castle Underground Station",
            "predicted_arrival": "2026-03-12T17:28:41+00:00",
            "scheduled_time": "2026-03-12T17:29:00+00:00",
            "variance_seconds": -19,
            "time_to_station": 991,
            "platform": "Northbound - Platform 4",
            "direction": ""
          },
          {
            "vehicle_id": "212",
            "destination": "Elephant & Castle Underground Station",
            "predicted_arrival": "2026-03-12T17:14:10+00:00",
            "scheduled_time": "2026-03-12T17:14:00+00:00",
            "variance_seconds": 10,
            "time_to_station": 120,
            "platform": "Northbound - Platform 3",
            "direction": ""
          },
          {
            "vehicle_id": "242",
            "destination": "Elephant & Castle Underground Station",
            "predicted_arrival": "2026-03-12T17:22:40+00:00",
            "scheduled_time": "2026-03-12T17:23:00+00:00",
            "variance_seconds": -20,
            "time_to_station": 630,
            "platform": "Northbound - Platform 3",
            "direction": ""
          }
        ]
      }
    },
    "timestamp": "2026-03-12T17:12:30.737631+00:00"
  },
  {
    "line_id": "hammersmith-city",
    "line_name": "Hammersmith & City",
    "colour": "#F3A9BB",
    "stations": {
      "940GZZLUHSC": {
        "name": "Hammersmith",
        "total_predictions": 12,
        "on_time": 5,
        "early": 6,
        "late": 1,
        "on_time_pct": 41.7,
        "avg_variance_secs": -101.7,
        "variances": [
          {
            "vehicle_id": "171",
            "destination": "Hammersmith (H&C Line) Underground Station",
            "predicted_arrival": "2026-03-12T17:36:11+00:00",
            "scheduled_time": "2026-03-12T17:40:00+00:00",
            "variance_seconds": -229,
            "time_to_station": 1428,
            "platform": "Eastbound - Platform 1",
            "direction": ""
          },
          {
            "vehicle_id": "202",
            "destination": "Hammersmith (H&C Line) Underground Station",
            "predicted_arrival": "2026-03-12T17:40:11+00:00",
            "scheduled_time": "2026-03-12T17:40:00+00:00",
            "variance_seconds": 11,
            "time_to_station": 1668,
            "platform": "Eastbound - Platform 1",
            "direction": ""
          },
          {
            "vehicle_id": "200",
            "destination": "Hammersmith (H&C Line) Underground Station",
            "predicted_arrival": "2026-03-12T17:16:41+00:00",
            "scheduled_time": "2026-03-12T17:20:00+00:00",
            "variance_seconds": -199,
            "time_to_station": 258,
            "platform": "Eastbound - Platform 2",
            "direction": ""
          },
          {
            "vehicle_id": "202",
            "destination": "Hammersmith (H&C Line) Underground Station",
            "predicted_arrival": "2026-03-12T17:40:11+00:00",
            "scheduled_time": "2026-03-12T17:40:00+00:00",
            "variance_seconds": 11,
            "time_to_station": 1668,
            "platform": "Eastbound - Platform 2",
            "direction": ""
          },
          {
            "vehicle_id": "264",
            "destination": "Hammersmith (H&C Line) Underground Station",
            "predicted_arrival": "2026-03-12T17:21:11+00:00",
            "scheduled_time": "2026-03-12T17:22:00+00:00",
            "variance_seconds": -49,
            "time_to_station": 528,
            "platform": "Eastbound - Platform 3",
            "direction": ""
          },
          {
            "vehicle_id": "200",
            "destination": "Hammersmith (H&C Line) Underground Station",
            "predicted_arrival": "2026-03-12T17:16:11+00:00",
            "scheduled_time": "2026-03-12T17:20:00+00:00",
            "variance_seconds": -229,
            "time_to_station": 228,
            "platform": "Eastbound - Platform 3",
            "direction": ""
          },
          {
            "vehicle_id": "171",
            "destination": "Hammersmith (H&C Line) Underground Station",
            "predicted_arrival": "2026-03-12T17:36:11+00:00",
            "scheduled_time": "2026-03-12T17:40:00+00:00",
            "variance_seconds": -229,
            "time_to_station": 1428,
            "platform": "Eastbound - Platform 3",
            "direction": ""
          },
          {
            "vehicle_id": "202",
            "destination": "Hammersmith (H&C Line) Underground Station",
            "predicted_arrival": "2026-03-12T17:36:11+00:00",
            "scheduled_time": "2026-03-12T17:40:00+00:00",
            "variance_seconds": -229,
            "time_to_station": 1428,
            "platform": "Eastbound - Platform 3",
            "direction": ""
          },
          {
            "vehicle_id": "264",
            "destination": "Hammersmith (H&C Line) Underground Station",
            "predicted_arrival": "2026-03-12T17:20:11+00:00",
            "scheduled_time": "2026-03-12T17:20:00+00:00",
            "variance_seconds": 11,
            "time_to_station": 468,
            "platform": "Eastbound - Platform 2",
            "direction": ""
          },
          {
            "vehicle_id": "200",
            "destination": "Hammersmith (H&C Line) Underground Station",
            "predicted_arrival": "2026-03-12T17:16:10+00:00",
            "scheduled_time": "2026-03-12T17:20:00+00:00",
            "variance_seconds": -230,
            "time_to_station": 227,
            "platform": "Eastbound - Platform 1",
            "direction": ""
          },
          {
            "vehicle_id": "264",
            "destination": "Hammersmith (H&C Line) Underground Station",
            "predicted_arrival": "2026-03-12T17:20:10+00:00",
            "scheduled_time": "2026-03-12T17:20:00+00:00",
            "variance_seconds": 10,
            "time_to_station": 467,
            "platform": "Eastbound - Platform 1",
            "direction": ""
          },
          {
            "vehicle_id": "171",
            "destination": "Hammersmith (H&C Line) Underground Station",
            "predicted_arrival": "2026-03-12T17:34:11+00:00",
            "scheduled_time": "2026-03-12T17:32:00+00:00",
            "variance_seconds": 131,
            "time_to_station": 1308,
            "platform": "Eastbound - Platform 2",
            "direction": ""
          }
        ]
      },
      "940GZZLUBST": {
        "name": "Baker Street",
        "total_predictions": 0,
        "on_time": 0,
        "early": 0,
        "late": 0,
        "on_time_pct": 0,
        "avg_variance_secs": 0,
        "variances": []
      },
      "940GZZLUKSX": {
        "name": "King's Cross St. Pancras",
        "total_predictions": 0,
        "on_time": 0,
        "early": 0,
        "late": 0,
        "on_time_pct": 0,
        "avg_variance_secs": 0,
        "variances": []
      },
      "940GZZLULVT": {
        "name": "Liverpool Street",
        "total_predictions": 0,
        "on_time": 0,
        "early": 0,
        "late": 0,
        "on_time_pct": 0,
        "avg_variance_secs": 0,
        "variances": []
      },
      "940GZZLUBKG": {
        "name": "Barking",
        "total_predictions": 8,
        "on_time": 6,
        "early": 1,
        "late": 1,
        "on_time_pct": 75.0,
        "avg_variance_secs": 3.5,
        "variances": [
          {
            "vehicle_id": "271",
            "destination": "Hammersmith (H&C Line) Underground Station",
            "predicted_arrival": "2026-03-12T17:14:41+00:00",
            "scheduled_time": "2026-03-12T17:14:00+00:00",
            "variance_seconds": 41,
            "time_to_station": 138,
            "platform": "Westbound - Platform 6",
            "direction": "inbound"
          },
          {
            "vehicle_id": "041",
            "destination": "unknown",
            "predicted_arrival": "2026-03-12T17:23:11+00:00",
            "scheduled_time": "2026-03-12T17:23:00+00:00",
            "variance_seconds": 11,
            "time_to_station": 648,
            "platform": "Westbound - Platform 3",
            "direction": ""
          },
          {
            "vehicle_id": "043",
            "destination": "unknown",
            "predicted_arrival": "2026-03-12T17:38:11+00:00",
            "scheduled_time": "2026-03-12T17:39:00+00:00",
            "variance_seconds": -49,
            "time_to_station": 1548,
            "platform": "Westbound - Platform 3",
            "direction": ""
          },
          {
            "vehicle_id": "273",
            "destination": "Barking Underground Station",
            "predicted_arrival": "2026-03-12T17:13:11+00:00",
            "scheduled_time": "2026-03-12T17:14:00+00:00",
            "variance_seconds": -49,
            "time_to_station": 48,
            "platform": "Eastbound - Platform 2",
            "direction": ""
          },
          {
            "vehicle_id": "272",
            "destination": "Hammersmith (H&C Line) Underground Station",
            "predicted_arrival": "2026-03-12T17:23:11+00:00",
            "scheduled_time": "2026-03-12T17:23:00+00:00",
            "variance_seconds": 11,
            "time_to_station": 648,
            "platform": "Westbound - Platform 6",
            "direction": "inbound"
          },
          {
            "vehicle_id": "276",
            "destination": "Barking Underground Station",
            "predicted_arrival": "2026-03-12T17:15:41+00:00",
            "scheduled_time": "2026-03-12T17:14:00+00:00",
            "variance_seconds": 101,
            "time_to_station": 198,
            "platform": "Eastbound - Platform 2",
            "direction": ""
          },
          {
            "vehicle_id": "273",
            "destination": "unknown",
            "predicted_arrival": "2026-03-12T17:35:11+00:00",
            "scheduled_time": "2026-03-12T17:33:00+00:00",
            "variance_seconds": 131,
            "time_to_station": 1368,
            "platform": "Westbound - Platform 6",
            "direction": ""
          },
          {
            "vehicle_id": "036",
            "destination": "unknown",
            "predicted_arrival": "2026-03-12T17:36:11+00:00",
            "scheduled_time": "2026-03-12T17:39:00+00:00",
            "variance_seconds": -169,
            "time_to_station": 1428,
            "platform": "Westbound - Platform 6",
            "direction": ""
          }
        ]
      }
    },
    "timestamp": "2026-03-12T17:12:31.917937+00:00"
  },
  {
    "line_id": "circle",
    "line_name": "Circle",
    "colour": "#FFD300",
    "stations": {
      "940GZZLUHSC": {
        "name": "Hammersmith",
        "total_predictions": 0,
        "on_time": 0,
        "early": 0,
        "late": 0,
        "on_time_pct": 0,
        "avg_variance_secs": 0,
        "variances": []
      },
      "940GZZLUBST": {
        "name": "Baker Street",
        "total_predictions": 0,
        "on_time": 0,
        "early": 0,
        "late": 0,
        "on_time_pct": 0,
        "avg_variance_secs": 0,
        "variances": []
      },
      "940GZZLUKSX": {
        "name": "King's Cross St. Pancras",
        "total_predictions": 0,
        "on_time": 0,
        "early": 0,
        "late": 0,
        "on_time_pct": 0,
        "avg_variance_secs": 0,
        "variances": []
      },
      "940GZZLULVT": {
        "name": "Liverpool Street",
        "total_predictions": 0,
        "on_time": 0,
        "early": 0,
        "late": 0,
        "on_time_pct": 0,
        "avg_variance_secs": 0,
        "variances": []
      },
      "940GZZLUEMB": {
        "name": "Embankment",
        "total_predictions": 0,
        "on_time": 0,
        "early": 0,
        "late": 0,
        "on_time_pct": 0,
        "avg_variance_secs": 0,
        "variances": []
      }
    },
    "timestamp": "2026-03-12T17:12:33.134942+00:00"
  }
]